[
	"# TRADING HOUSE PLATFORM",
	{
	"model": "ex_de_docks_steps_01",
	"x": -11699.271,
	"y": -70396.516,
	"z": 270.629,
	"r": 0,
	"scale": 1.03
	},
	{
	"model": "ex_common_plat_end",
	"x": -11904.000,
	"y": -70400.000,
	"z": 320,
	"r": 0
	},
	{
	"model": "ex_common_plat_cent",
	"x": -12160.000,
	"y": -70400.000,
	"z": 320.000,
	"r": 360
	},
	{
	"model": "ex_common_plat_corn",
	"x": -12416.000,
	"y": -70400.000,
	"z": 320.000,
	"r": 0
	},
	{
	"model": "ex_common_plat_cent",
	"x": -12416.000,
	"y": -70144.000,
	"z": 320.000,
	"r": 270
	},
	{
	"model": "ex_common_plat_end",
	"x": -12416.000,
	"y": -69888.000,
	"z": 320.000,
	"r": 270
	},

	"# TRADING HOUSE",
	{
	"model": "ex_common_house_tall_02",
	"x": -12136.000,
	"y": -70368.000,
	"z": 952.000,
	"r": 270
	},
	{
	"model": "ex_nord_win_01",
	"x": -11926.264,
	"y": -70250.680,
	"z": 499.912,
	"r": 0
	},
	{
	"model": "ex_nord_win_02",
	"x": -12136.906,
	"y": -70245.742,
	"z": 502.614,
	"r": 0
	},
	{
	"model": "ex_nord_win_02",
	"x": -12279.225,
	"y": -69875.273,
	"z": 503.555,
	"r": 270
	},
	{
	"model": "ex_nord_win_01",
	"x": -12283.903,
	"y": -69888.875,
	"z": 717.221,
	"r": 270
	},
	{
	"model": "ex_nord_win_02",
	"x": -12287.744,
	"y": -70074.320,
	"z": 720.052,
	"r": 270
	}
	
]